winmem/__init__.py
winmem/exceptions.py
winmem/flags.py
winmem/imports.py
winmem/kernel_utils.py
winmem/memory.py
winmem/memory_classes.py
winmem/types.py
winmem-0.0.9.dist-info/LICENSE
winmem-0.0.9.dist-info/METADATA
winmem-0.0.9.dist-info/WHEEL
winmem-0.0.9.dist-info/top_level.txt
winmem-0.0.9.dist-info/RECORD
