Metadata-Version: 2.1
Name: winmem
Version: 0.0.9
Summary: Work easy with memory. (Windows ONLY)
Home-page: https://github.com/Pixelsuft/winmem
Author: Pixelsuft
License: MIT
Project-URL: Readme, https://github.com/Pixelsuft/winmem/blob/main/README.MD
Project-URL: Example, https://github.com/Pixelsuft/winmem/blob/main/main.py
Project-URL: Issue tracker, https://github.com/Pixelsuft/winmem/issues
Project-URL: Pull requests, https://github.com/Pixelsuft/winmem/pulls
Keywords: winmem
Platform: UNKNOWN
Classifier: License :: OSI Approved :: MIT License
Classifier: Programming Language :: Python :: 3.6
Classifier: Programming Language :: Python :: 3.7
Classifier: Programming Language :: Python :: 3.8
Classifier: Programming Language :: Python :: 3.9
Requires-Python: >=3.6
License-File: LICENSE
Requires-Dist: pywin32
Requires-Dist: psutil
Requires-Dist: typing
Requires-Dist: pefile
Requires-Dist: enums.py
